woppy/__init__.py
woppy/category.py
woppy/media.py
woppy/plugin.py
woppy/post.py
woppy/tag.py
woppy-1.0.0.dist-info/LICENSE
woppy-1.0.0.dist-info/METADATA
woppy-1.0.0.dist-info/WHEEL
woppy-1.0.0.dist-info/top_level.txt
woppy-1.0.0.dist-info/RECORD
