Metadata-Version: 2.1
Name: woppy
Version: 1.0.0
Summary: A Python library to manage WordPress sites via the REST API
Home-page: https://techard.net
Author: Techard
Author-email: info@techard.net
Maintainer: Fatih Zor
Maintainer-email: me@fatihzor.dev
License: MIT
Keywords: wordpress,rest api,api,cms
Platform: any
Classifier: Programming Language :: Python :: 3
Classifier: License :: OSI Approved :: MIT License
Classifier: Operating System :: OS Independent
Requires-Python: >=3.6
License-File: LICENSE
Requires-Dist: requests
